{"timecodes": [{"timecode": 0, "image": {"small": "content/H1s_uNrkl/slide_00000-small.jpeg", "large": "content/H1s_uNrkl/slide_00000-large.jpeg"}}, {"timecode": 61666, "image": {"small": "content/H1s_uNrkl/slide_00001-small.jpeg", "large": "content/H1s_uNrkl/slide_00001-large.jpeg"}}, {"timecode": 63333, "image": {"small": "content/H1s_uNrkl/slide_00002-small.jpeg", "large": "content/H1s_uNrkl/slide_00002-large.jpeg"}}, {"timecode": 76666, "image": {"small": "content/H1s_uNrkl/slide_00003-small.jpeg", "large": "content/H1s_uNrkl/slide_00003-large.jpeg"}}, {"timecode": 100166, "image": {"small": "content/H1s_uNrkl/slide_00004-small.jpeg", "large": "content/H1s_uNrkl/slide_00004-large.jpeg"}}, {"timecode": 163333, "image": {"small": "content/H1s_uNrkl/slide_00005-small.jpeg", "large": "content/H1s_uNrkl/slide_00005-large.jpeg"}}, {"timecode": 165500, "image": {"small": "content/H1s_uNrkl/slide_00006-small.jpeg", "large": "content/H1s_uNrkl/slide_00006-large.jpeg"}}, {"timecode": 168166, "image": {"small": "content/H1s_uNrkl/slide_00007-small.jpeg", "large": "content/H1s_uNrkl/slide_00007-large.jpeg"}}, {"timecode": 207500, "image": {"small": "content/H1s_uNrkl/slide_00008-small.jpeg", "large": "content/H1s_uNrkl/slide_00008-large.jpeg"}}, {"timecode": 210000, "image": {"small": "content/H1s_uNrkl/slide_00009-small.jpeg", "large": "content/H1s_uNrkl/slide_00009-large.jpeg"}}, {"timecode": 274166, "image": {"small": "content/H1s_uNrkl/slide_00010-small.jpeg", "large": "content/H1s_uNrkl/slide_00010-large.jpeg"}}, {"timecode": 276833, "image": {"small": "content/H1s_uNrkl/slide_00011-small.jpeg", "large": "content/H1s_uNrkl/slide_00011-large.jpeg"}}, {"timecode": 382666, "image": {"small": "content/H1s_uNrkl/slide_00012-small.jpeg", "large": "content/H1s_uNrkl/slide_00012-large.jpeg"}}, {"timecode": 417333, "image": {"small": "content/H1s_uNrkl/slide_00013-small.jpeg", "large": "content/H1s_uNrkl/slide_00013-large.jpeg"}}, {"timecode": 420500, "image": {"small": "content/H1s_uNrkl/slide_00014-small.jpeg", "large": "content/H1s_uNrkl/slide_00014-large.jpeg"}}, {"timecode": 450833, "image": {"small": "content/H1s_uNrkl/slide_00015-small.jpeg", "large": "content/H1s_uNrkl/slide_00015-large.jpeg"}}, {"timecode": 481000, "image": {"small": "content/H1s_uNrkl/slide_00016-small.jpeg", "large": "content/H1s_uNrkl/slide_00016-large.jpeg"}}, {"timecode": 511166, "image": {"small": "content/H1s_uNrkl/slide_00017-small.jpeg", "large": "content/H1s_uNrkl/slide_00017-large.jpeg"}}, {"timecode": 519833, "image": {"small": "content/H1s_uNrkl/slide_00018-small.jpeg", "large": "content/H1s_uNrkl/slide_00018-large.jpeg"}}, {"timecode": 552666, "image": {"small": "content/H1s_uNrkl/slide_00019-small.jpeg", "large": "content/H1s_uNrkl/slide_00019-large.jpeg"}}], "chapters": null, "errorCode": null, "sources": [], "id": "H1s_uNrkl", "category": "1477058816111", "cut": [], "title": "Python 3.6: utilisation des f-strings (PEP 498)", "pictures": [], "state": 12, "packageType": "tar", "type": "youtube", "thumbnail": "content/H1s_uNrkl/thumbnail.jpg", "lastState": "directoryCleaned", "metadata": {"profile": "2", "audio-input": "analog-line", "storage-directory": "/data/2016-10-15_08-40-17", "groups": ["S1BJh5Xyl", "B1fFuxNU"], "stream": false, "date": 1476520817, "rich-media": true, "sources": {"slides": {"width": 1920, "par": "1/1", "height": 1080, "framerate": 60, "interlaced": false}, "camera": {"width": 1920, "par": "1/1", "height": 1080, "framerate": 50, "interlaced": false}}, "user": "Byo5s571x", "template": "camera-only", "profile-settings": {"video-bitrate": 2000000, "video-height": 720, "audio-bitrate": 128000, "id": "2", "name": "HD"}, "duration": 838, "filename": "video.mp4", "id": "2016-10-15_08-40-17", "template-absolute": {"width": 1280, "boxes": [{"z": 0, "source": "camera", "height": 720, "width": 1280, "y": 0, "x": 0, "element": "camera-scale-raw"}], "height": 720}}, "available": true, "originalPackagePath": "/home/box/2016-10-15_08-40-17_rich-media.tar", "mediaId": "dRGlqSjB9zM", "description": "Il est pr\u00e9vu que la version stable de Python 3.6 inclue les f-strings d\u00e9finies dans PEP 498 (elles sont pr\u00e9sentes dans les versions non-d\u00e9finitives de Python 3.6 depuis alpha 1). Les f-strings sont la quatri\u00e8me forme de \"mise en forme composite\" (string interpolation) apr\u00e8s %-format, str.format(), et string.Template. Cette nouvelle fa\u00e7on de construire des cha\u00eenes am\u00e9liore souvent la lisibilit\u00e9 du code. Je propose de passer en revue ce que sont les f-strings, leurs particularit\u00e9s et certains d\u00e9tails de leur impl\u00e9mentation dans CPython.", "views": 1, "link": "/publish/video/H1s_uNrkl", "date": 1476520817000, "properties": {"ryf3vyHJx": "Ludovic VAUGEOIS", "1438782304240": ""}, "originalFileName": "2016-10-15_08-40-17_rich-media", "lastTransition": null}